sym/__init__.py
sym/atan_camera_cal.py
sym/double_sphere_camera_cal.py
sym/equirectangular_camera_cal.py
sym/linear_camera_cal.py
sym/orthographic_camera_cal.py
sym/polynomial_camera_cal.py
sym/pose2.py
sym/pose3.py
sym/py.typed
sym/rot2.py
sym/rot3.py
sym/spherical_camera_cal.py
sym/unit3.py
sym/ops/__init__.py
sym/ops/atan_camera_cal/__init__.py
sym/ops/atan_camera_cal/camera_ops.py
sym/ops/atan_camera_cal/group_ops.py
sym/ops/atan_camera_cal/lie_group_ops.py
sym/ops/double_sphere_camera_cal/__init__.py
sym/ops/double_sphere_camera_cal/camera_ops.py
sym/ops/double_sphere_camera_cal/group_ops.py
sym/ops/double_sphere_camera_cal/lie_group_ops.py
sym/ops/equirectangular_camera_cal/__init__.py
sym/ops/equirectangular_camera_cal/camera_ops.py
sym/ops/equirectangular_camera_cal/group_ops.py
sym/ops/equirectangular_camera_cal/lie_group_ops.py
sym/ops/linear_camera_cal/__init__.py
sym/ops/linear_camera_cal/camera_ops.py
sym/ops/linear_camera_cal/group_ops.py
sym/ops/linear_camera_cal/lie_group_ops.py
sym/ops/orthographic_camera_cal/__init__.py
sym/ops/orthographic_camera_cal/camera_ops.py
sym/ops/orthographic_camera_cal/group_ops.py
sym/ops/orthographic_camera_cal/lie_group_ops.py
sym/ops/polynomial_camera_cal/__init__.py
sym/ops/polynomial_camera_cal/camera_ops.py
sym/ops/polynomial_camera_cal/group_ops.py
sym/ops/polynomial_camera_cal/lie_group_ops.py
sym/ops/pose2/__init__.py
sym/ops/pose2/group_ops.py
sym/ops/pose2/lie_group_ops.py
sym/ops/pose3/__init__.py
sym/ops/pose3/group_ops.py
sym/ops/pose3/lie_group_ops.py
sym/ops/rot2/__init__.py
sym/ops/rot2/group_ops.py
sym/ops/rot2/lie_group_ops.py
sym/ops/rot3/__init__.py
sym/ops/rot3/group_ops.py
sym/ops/rot3/lie_group_ops.py
sym/ops/spherical_camera_cal/__init__.py
sym/ops/spherical_camera_cal/camera_ops.py
sym/ops/spherical_camera_cal/group_ops.py
sym/ops/spherical_camera_cal/lie_group_ops.py
sym/ops/unit3/__init__.py
sym/ops/unit3/group_ops.py
sym/ops/unit3/lie_group_ops.py
symforce_sym-0.10.1.dist-info/METADATA
symforce_sym-0.10.1.dist-info/WHEEL
symforce_sym-0.10.1.dist-info/top_level.txt
symforce_sym-0.10.1.dist-info/RECORD
